cacheback/__init__.py
cacheback/cache_back.py
cacheback/cli.py
cacheback/dependency.py
cacheback/headers.py
cacheback-0.2.0.dist-info/METADATA
cacheback-0.2.0.dist-info/WHEEL
cacheback-0.2.0.dist-info/top_level.txt
cacheback-0.2.0.dist-info/RECORD
