Metadata-Version: 2.1
Name: cacheback
Version: 0.2.0
Summary: Cache Back library for IDP 2022-23
Home-page: UNKNOWN
Author: Ashish Patel, Jeein Kim
License: MIT
Platform: UNKNOWN
Requires-Dist: SQLAlchemy (==1.4.45)
Requires-Dist: numpy (==1.23.5)
Requires-Dist: pandas (==1.5.2)
Requires-Dist: psycopg2-binary (==2.9.5)
Requires-Dist: wheel (==0.38.4)
